AzizKitten/__init__.py
AzizKitten/acos.py
AzizKitten/acot.py
AzizKitten/acsc.py
AzizKitten/among_us.py
AzizKitten/asec.py
AzizKitten/asin.py
AzizKitten/atan.py
AzizKitten/bin_rep.py
AzizKitten/cbrt.py
AzizKitten/ceil.py
AzizKitten/constants.py
AzizKitten/cos.py
AzizKitten/cosh.py
AzizKitten/cot.py
AzizKitten/coth.py
AzizKitten/csc.py
AzizKitten/csch.py
AzizKitten/cubic.py
AzizKitten/degrees.py
AzizKitten/derivative.py
AzizKitten/exp.py
AzizKitten/factorial.py
AzizKitten/floor.py
AzizKitten/gcd.py
AzizKitten/integrate.py
AzizKitten/is_prime.py
AzizKitten/lcm.py
AzizKitten/ln.py
AzizKitten/log.py
AzizKitten/ment_calc.py
AzizKitten/mystery.py
AzizKitten/quad.py
AzizKitten/quartic.py
AzizKitten/quintic.py
AzizKitten/radians.py
AzizKitten/sec.py
AzizKitten/sech.py
AzizKitten/sin.py
AzizKitten/sinh.py
AzizKitten/sqrt.py
AzizKitten/tan.py
AzizKitten/tanh.py
AzizKitten-11.7.3.dist-info/LICENSE
AzizKitten-11.7.3.dist-info/METADATA
AzizKitten-11.7.3.dist-info/WHEEL
AzizKitten-11.7.3.dist-info/top_level.txt
AzizKitten-11.7.3.dist-info/RECORD
