Metadata-Version: 2.1
Name: AzizKitten
Version: 11.7.3
Summary: AzizOmrane's own Python package
Author: AzizKitten
Author-email: AzizKitten <azizprv43@gmail.com>
Project-URL: AboutMe, https://azizkitten.github.io
Project-URL: Documentation, https://azizkitten.github.io/python
Project-URL: Bug Tracker, https://github.com/AzizKitten/azizkitten.github.io/issues
Classifier: Programming Language :: Python :: 3
Classifier: License :: OSI Approved :: MIT License
Classifier: Operating System :: OS Independent
Requires-Python: >=3.10
License-File: LICENSE
